word2tei/__init__.py
word2tei/_modidx.py
word2tei/core.py
word2tei-0.0.1.dist-info/LICENSE
word2tei-0.0.1.dist-info/METADATA
word2tei-0.0.1.dist-info/WHEEL
word2tei-0.0.1.dist-info/entry_points.txt
word2tei-0.0.1.dist-info/top_level.txt
word2tei-0.0.1.dist-info/RECORD
